{"env":"mac","testType":"unit","testFrame":"testng","productId":0,"taskId":0,"zentaoData":"","buildUrl":"","pass":3,"fail":0,"skip":0,"total":3,"startTime":0,"endTime":0,"duration":1,"funcResult":null,"unitResult":[{"title":"loginSuccess","testSuite":"com.ngtesting.autotest.test.login.TestLogin","startTime":0,"endTime":0,"duration":1.011,"failure":null,"id":1,"status":"pass"},{"title":"loginFail","testSuite":"com.ngtesting.autotest.test.login.TestLogin","startTime":0,"endTime":0,"duration":0,"failure":null,"id":2,"status":"pass"},{"title":"loginFail","testSuite":"com.ngtesting.autotest.test.login.TestLogin","startTime":0,"endTime":0,"duration":0.001,"failure":null,"id":3,"status":"pass"}]}